pyUSIrest/__init__.py
pyUSIrest/auth.py
pyUSIrest/client.py
pyUSIrest/exceptions.py
pyUSIrest/settings.py
pyUSIrest/usi.py
pyUSIrest-0.3.1.dist-info/AUTHORS.rst
pyUSIrest-0.3.1.dist-info/LICENSE
pyUSIrest-0.3.1.dist-info/METADATA
pyUSIrest-0.3.1.dist-info/WHEEL
pyUSIrest-0.3.1.dist-info/top_level.txt
pyUSIrest-0.3.1.dist-info/RECORD
