Metadata-Version: 2.1
Name: pyUSIrest
Version: 0.3.1
Summary: Python USI submission REST API contain all methods to interact with EMBL-EBI Unified Submissions Interface
Home-page: https://github.com/cnr-ibba/pyUSIrest
Author: Paolo Cozzi
Author-email: paolo.cozzi@ibba.cnr.it
License: GNU General Public License v3
Keywords: pyUSIrest
Platform: UNKNOWN
Classifier: Development Status :: 4 - Beta
Classifier: Intended Audience :: Developers
Classifier: Intended Audience :: Science/Research
Classifier: License :: OSI Approved :: GNU General Public License v3 (GPLv3)
Classifier: Natural Language :: English
Classifier: Programming Language :: Python :: 3
Classifier: Programming Language :: Python :: 3.5
Classifier: Programming Language :: Python :: 3.6
Classifier: Programming Language :: Python :: 3.7
Classifier: Programming Language :: Python :: 3.8
Requires-Python: >=3.5
Requires-Dist: python-jwt
Requires-Dist: requests
Requires-Dist: url-normalize
Requires-Dist: dateutils
